lmi/__init__.py
lmi/__init__.pyi
lmi/helpers.py
lmi/lmi.cpython-311-x86_64-linux-gnu.so
lmi/py.typed
lmi/utils.py
lmi/__pycache__/__init__.cpython-311.pyc
lmi/__pycache__/helpers.cpython-311.pyc
lmi/__pycache__/utils.cpython-311.pyc
lmi_rs.libs/libgfortran-58726230.so.5.0.0
lmi_rs.libs/libquadmath-a92b999f.so.0.0.0
lmi_rs-0.5.2.dist-info/METADATA
lmi_rs-0.5.2.dist-info/WHEEL
lmi_rs-0.5.2.dist-info/RECORD
