Metadata-Version: 2.4
Name: lmi-rs
Version: 0.5.2
Classifier: Programming Language :: Rust
Classifier: Programming Language :: Python :: 3
Classifier: Operating System :: OS Independent
Summary: Learned Metric Index (LMI)
Author-email: Marek Ličko <mareklicko448@gmail.com>
License: MIT
Requires-Python: >=3.11
